{
  "conditions": [
    {
      "type": "forge:and",
      "values": [
        {
          "type": "armorplus:enabled"
        },
        {
          "type": "minecraft:item_exists",
          "item": "armorplus:super_star_chestplate"
        }
      ]
    }
  ],
  "group": "armor",
  "type": "minecraft:crafting_shaped",
  "pattern": [
    "# #",
    "###",
    "###"
  ],
  "key": {
    "#": {
      "item": "#wither_bone"
    }
  },
  "result": {
    "item": "armorplus:super_star_chestplate"
  }
}
